README.rst
setup.py
helixpc/__init__.py
helixpc/_version.py
helixpc/cli.py
helixpc/graph_genes.py
helixpc/group_genes.py
helixpc.egg-info/PKG-INFO
helixpc.egg-info/SOURCES.txt
helixpc.egg-info/dependency_links.txt
helixpc.egg-info/entry_points.txt
helixpc.egg-info/requires.txt
helixpc.egg-info/top_level.txt