Metadata-Version: 1.0
Name: helixpc
Version: 1.2.1
Summary: Automisation of graph generation for gene FC databases.
Home-page: https://github.com/Gathaspa/HelixPC
Author: Anne-Laure Ehresmann
Author-email: alehresmann@gmail.com
License: MIT
Platform: UNKNOWN
